<?xml version="1.0" encoding="UTF-8"?>
<Bucket
   type = "1"
   version = "2.0">
   <Breakpoints>
      <BreakpointProxy
         BreakpointExtensionID = "Xcode.Breakpoint.FileBreakpoint">
         <BreakpointContent
            shouldBeEnabled = "No"
            ignoreCount = "0"
            continueAfterRunningActions = "No"
            filePath = "Where_is_my_car/ViewController.swift"
            timestampString = "514045459.706598"
            startingColumnNumber = "9223372036854775807"
            endingColumnNumber = "9223372036854775807"
            startingLineNumber = "55"
            endingLineNumber = "55"
            landmarkName = "locationManager(_:didUpdateLocations:)"
            landmarkType = "7">
         </BreakpointContent>
      </BreakpointProxy>
      <BreakpointProxy
         BreakpointExtensionID = "Xcode.Breakpoint.FileBreakpoint">
         <BreakpointContent
            shouldBeEnabled = "No"
            ignoreCount = "0"
            continueAfterRunningActions = "No"
            filePath = "Where_is_my_car/ViewController.swift"
            timestampString = "514045459.706598"
            startingColumnNumber = "9223372036854775807"
            endingColumnNumber = "9223372036854775807"
            startingLineNumber = "65"
            endingLineNumber = "65"
            landmarkName = "saveTap(_:)"
            landmarkType = "7">
         </BreakpointContent>
      </BreakpointProxy>
      <BreakpointProxy
         BreakpointExtensionID = "Xcode.Breakpoint.FileBreakpoint">
         <BreakpointContent
            shouldBeEnabled = "No"
            ignoreCount = "0"
            continueAfterRunningActions = "No"
            filePath = "Where_is_my_car/AddViewController.swift"
            timestampString = "515355930.154721"
            startingColumnNumber = "9223372036854775807"
            endingColumnNumber = "9223372036854775807"
            startingLineNumber = "81"
            endingLineNumber = "81"
            landmarkName = "onSave(_:)"
            landmarkType = "7">
         </BreakpointContent>
      </BreakpointProxy>
      <BreakpointProxy
         BreakpointExtensionID = "Xcode.Breakpoint.FileBreakpoint">
         <BreakpointContent
            shouldBeEnabled = "No"
            ignoreCount = "0"
            continueAfterRunningActions = "No"
            filePath = "Where_is_my_car/TableViewController.swift"
            timestampString = "515355450.351523"
            startingColumnNumber = "9223372036854775807"
            endingColumnNumber = "9223372036854775807"
            startingLineNumber = "74"
            endingLineNumber = "74"
            landmarkName = "tableView(_:didSelectRowAt:)"
            landmarkType = "7">
         </BreakpointContent>
      </BreakpointProxy>
      <BreakpointProxy
         BreakpointExtensionID = "Xcode.Breakpoint.FileBreakpoint">
         <BreakpointContent
            shouldBeEnabled = "No"
            ignoreCount = "0"
            continueAfterRunningActions = "No"
            filePath = "Where_is_my_car/DetailsViewController.swift"
            timestampString = "514060865.446195"
            startingColumnNumber = "9223372036854775807"
            endingColumnNumber = "9223372036854775807"
            startingLineNumber = "17"
            endingLineNumber = "17"
            landmarkName = "DetailsViewController"
            landmarkType = "3">
            <Locations>
               <Location
                  shouldBeEnabled = "Yes"
                  ignoreCount = "0"
                  continueAfterRunningActions = "No"
                  symbolName = "Where_is_my_car.DetailsViewController.commentLabel.getter : weak Swift.ImplicitlyUnwrappedOptional&lt;__ObjC.UILabel&gt;"
                  moduleName = "Where_is_my_car"
                  usesParentBreakpointCondition = "Yes"
                  urlString = "file:///Users/MaximeG/Desktop/Where_is_my_car/Where_is_my_car/DetailsViewController.swift"
                  timestampString = "514060867.951402"
                  startingColumnNumber = "9223372036854775807"
                  endingColumnNumber = "9223372036854775807"
                  startingLineNumber = "17"
                  endingLineNumber = "17"
                  offsetFromSymbolStart = "34">
               </Location>
               <Location
                  shouldBeEnabled = "Yes"
                  ignoreCount = "0"
                  continueAfterRunningActions = "No"
                  symbolName = "Where_is_my_car.DetailsViewController.commentLabel.setter : weak Swift.ImplicitlyUnwrappedOptional&lt;__ObjC.UILabel&gt;"
                  moduleName = "Where_is_my_car"
                  usesParentBreakpointCondition = "Yes"
                  urlString = "file:///Users/MaximeG/Desktop/Where_is_my_car/Where_is_my_car/DetailsViewController.swift"
                  timestampString = "514060867.966262"
                  startingColumnNumber = "9223372036854775807"
                  endingColumnNumber = "9223372036854775807"
                  startingLineNumber = "17"
                  endingLineNumber = "17"
                  offsetFromSymbolStart = "47">
               </Location>
               <Location
                  shouldBeEnabled = "Yes"
                  ignoreCount = "0"
                  continueAfterRunningActions = "No"
                  symbolName = "Where_is_my_car.DetailsViewController.init (nibName : Swift.Optional&lt;Swift.String&gt;, bundle : Swift.Optional&lt;__ObjC.Bundle&gt;) -&gt; Where_is_my_car.DetailsViewController"
                  moduleName = "Where_is_my_car"
                  usesParentBreakpointCondition = "Yes"
                  urlString = "file:///Users/MaximeG/Desktop/Where_is_my_car/Where_is_my_car/DetailsViewController.swift"
                  timestampString = "514060867.968475"
                  startingColumnNumber = "9223372036854775807"
                  endingColumnNumber = "9223372036854775807"
                  startingLineNumber = "17"
                  endingLineNumber = "17"
                  offsetFromSymbolStart = "378">
               </Location>
               <Location
                  shouldBeEnabled = "Yes"
                  ignoreCount = "0"
                  continueAfterRunningActions = "No"
                  symbolName = "Where_is_my_car.DetailsViewController.init (coder : __ObjC.NSCoder) -&gt; Swift.Optional&lt;Where_is_my_car.DetailsViewController&gt;"
                  moduleName = "Where_is_my_car"
                  usesParentBreakpointCondition = "Yes"
                  urlString = "file:///Users/MaximeG/Desktop/Where_is_my_car/Where_is_my_car/DetailsViewController.swift"
                  timestampString = "514060867.97056"
                  startingColumnNumber = "9223372036854775807"
                  endingColumnNumber = "9223372036854775807"
                  startingLineNumber = "17"
                  endingLineNumber = "17"
                  offsetFromSymbolStart = "295">
               </Location>
            </Locations>
         </BreakpointContent>
      </BreakpointProxy>
   </Breakpoints>
</Bucket>
